flask_alchemist/__init__.py
flask_alchemist-1.0.2.dist-info/LICENSE
flask_alchemist-1.0.2.dist-info/METADATA
flask_alchemist-1.0.2.dist-info/WHEEL
flask_alchemist-1.0.2.dist-info/RECORD
