Metadata-Version: 2.1
Name: Flask-Alchemist
Version: 1.0.2
Summary: Flask extension for working with SQLAlchemy
License: MIT
Author: Rafal Padkowski
Author-email: rafaelp@poczta.onet.pl
Requires-Python: >=3.10
Classifier: License :: OSI Approved :: MIT License
Classifier: Programming Language :: Python :: 3
Classifier: Programming Language :: Python :: 3.10
Classifier: Programming Language :: Python :: 3.11
Classifier: Programming Language :: Python :: 3.12
Requires-Dist: flask (>=3.0.0)
Requires-Dist: sqlalchemy (>=2.0.0)
